trustifi/__init__.py
trustifi/__main__.py
trustifi/cacert.pem
trustifi/core.py
trustifi/py.typed
trustifi-29.dist-info/licenses/LICENSE
trustifi-29.dist-info/METADATA
trustifi-29.dist-info/WHEEL
trustifi-29.dist-info/top_level.txt
trustifi-29.dist-info/RECORD
